githide/__init__.py
githide/add_command.py
githide/cli.py
githide/init_command.py
githide/list_command.py
githide/remove_command.py
githide/undo_command.py
githide-0.1.0.dist-info/METADATA
githide-0.1.0.dist-info/WHEEL
githide-0.1.0.dist-info/entry_points.txt
githide-0.1.0.dist-info/top_level.txt
githide-0.1.0.dist-info/RECORD
