Metadata-Version: 2.1
Name: githide
Version: 0.1.0
Summary: A simple tool to hide files in a git repository without adding them to .gitignore.
Project-URL: Homepage, https://github.com/kyle-cassidy/githide
Classifier: Development Status :: 3 - Alpha
Classifier: Intended Audience :: Developers
Classifier: License :: OSI Approved :: MIT License
Classifier: Operating System :: OS Independent
Classifier: Programming Language :: Python :: 3
Requires-Python: >=3.12.2
Requires-Dist: click
